h2gis/__init__.py
h2gis/deserializer.py
h2gis/h2gis.py
h2gis/h2gisconnector.py
h2gis/lib/h2gis.dll
h2gis/lib/h2gis.so
h2gis-0.0.3.dist-info/METADATA
h2gis-0.0.3.dist-info/WHEEL
h2gis-0.0.3.dist-info/top_level.txt
h2gis-0.0.3.dist-info/RECORD
