Metadata-Version: 2.1
Name: h2gis
Version: 0.0.3
Summary: A Python library to use an H2GIS database through a native GraalVM bridge.
Home-page: https://github.com/orbisgis/h2gis
Author: Maël PHILIPPE, CNRS and Erwan BOCHER, CNRS
Classifier: Programming Language :: Python :: 3
Classifier: License :: OSI Approved :: GNU Lesser General Public License v3 (LGPLv3)
Classifier: Operating System :: OS Independent
Requires-Python: >=3.7
